ensurance/__init__.py
ensurance/ensure.py
ensurance-0.1.0.dist-info/METADATA
ensurance-0.1.0.dist-info/WHEEL
ensurance-0.1.0.dist-info/top_level.txt
ensurance-0.1.0.dist-info/RECORD
